qualle/__init__.py
qualle/evaluate.py
qualle/features/__init__.py
qualle/features/base.py
qualle/features/combined.py
qualle/features/confidence.py
qualle/features/label_calibration/__init__.py
qualle/features/label_calibration/base.py
qualle/features/label_calibration/simple_label_calibration.py
qualle/features/label_calibration/thesauri_label_calibration.py
qualle/features/text/__init__.py
qualle/features/text/count.py
qualle/interface/__init__.py
qualle/interface/cli.py
qualle/interface/config.py
qualle/interface/data/__init__.py
qualle/interface/data/annif.py
qualle/interface/data/tsv.py
qualle/interface/internal.py
qualle/interface/rest.py
qualle/label_calibration/__init__.py
qualle/label_calibration/category.py
qualle/label_calibration/simple.py
qualle/main.py
qualle/models.py
qualle/pipeline.py
qualle/quality_estimation.py
qualle/train.py
qualle/utils.py
qualle-0.5.2.dist-info/METADATA
qualle-0.5.2.dist-info/WHEEL
qualle-0.5.2.dist-info/entry_points.txt
qualle-0.5.2.dist-info/licenses/LICENSE
qualle-0.5.2.dist-info/RECORD
