Metadata-Version: 2.4
Name: qualle
Version: 0.5.2
Summary: A framework to predict the quality of a multi-label classification result
License: Apache-2.0
License-File: LICENSE
Author: AutoSE
Author-email: autose@zbw.eu
Requires-Python: >=3.10,<3.14
Classifier: Intended Audience :: Science/Research
Classifier: License :: OSI Approved :: Apache Software License
Classifier: Programming Language :: Python :: 3
Classifier: Programming Language :: Python :: 3.10
Classifier: Programming Language :: Python :: 3.11
Classifier: Programming Language :: Python :: 3.12
Classifier: Programming Language :: Python :: 3.13
Classifier: Topic :: Scientific/Engineering :: Artificial Intelligence
Requires-Dist: fastapi (>=0.124,<0.125)
Requires-Dist: numpy (==2.0.0)
Requires-Dist: pydantic (>=2.12,<2.13)
Requires-Dist: pydantic-settings (>=2.12,<2.13)
Requires-Dist: rdflib (>=7.1,<7.2)
Requires-Dist: scikit-learn (>=1.5,<1.6)
Requires-Dist: scipy (>=1.15,<1.16)
Requires-Dist: uvicorn (>=0.38,<0.39)
Project-URL: Homepage, https://github.com/zbw/qualle
